chfs/__init__.py
chfs/core.py
chfs/dask/__init__.py
chfs/dask/distributed.py
fsspec_chfs-0.0.1.dist-info/LICENSE
fsspec_chfs-0.0.1.dist-info/METADATA
fsspec_chfs-0.0.1.dist-info/WHEEL
fsspec_chfs-0.0.1.dist-info/entry_points.txt
fsspec_chfs-0.0.1.dist-info/top_level.txt
fsspec_chfs-0.0.1.dist-info/RECORD
