Metadata-Version: 2.1
Name: fsspec-chfs
Version: 0.0.1
Summary: Pythonic file system for CHFS
Home-page: https://github.com/donkomura/fsspec-chfs
Author: Kazuki Obata, Sohei Koyama
Author-email: obata@hpcs.cs.tsukuba.ac.jp, skoyama@hpcs.cs.tsukuba.ac.jp
License-File: LICENSE
Requires-Dist: pychfs (>=0.0.1)
